<package>
  <name>concert_service_teleop</name>
  <version>0.1.0</version>
  <description>
      Teleop by request from a rocon interactive program.
  </description>
  <maintainer email="d.stonier@gmail.com">Daniel Stonier</maintainer>
  <license>BSD</license>
  <url type="website">http://ros.org/wiki/concert_service_teleop</url>
  <url type="repository">https://github.com/robotics-in-concert/concert_services</url>
  <url type="bugtracker">https://github.com/robotics-in-concert/concert_services/issues</url>
  <author>Daniel Stonier</author>

  <buildtool_depend>catkin</buildtool_depend>

  <run_depend>rospy</run_depend>
  <run_depend>concert_msgs</run_depend>
  <run_depend>concert_scheduler_requests</run_depend>
  <run_depend>concert_service_utilities</run_depend>
  <run_depend>rocon_python_comms</run_depend>
  <run_depend>concert_service_msgs</run_depend>
  <run_depend>rocon_std_msgs</run_depend>
  <run_depend>scheduler_msgs</run_depend>
  <run_depend>unique_id</run_depend>

  <export>
    <concert_service>services/teleop/teleop.service</concert_service>
  </export>
</package>